{
  "partants": {
    "do for love ire f.ps. 3 a. | 05/02/2026 | chantilly | rond fille air | 1.600": {
      "horse": "DO FOR LOVE IRE F.PS. 3 a.",
      "horseUrl": "https://www.france-galop.com/fr/cheval/akpiWVhySklCTkJNVUJBU3NxWFJPZz09",
      "date": "05/02/2026",
      "track": "CHANTILLY",
      "race": "ROND FILLE AIR",
      "raceUrl": "https://www.france-galop.com/fr/course/detail/2026/P/NjBsTUU4d1JjejU1TlV1a2hweDJqdz09",
      "cat": "(Maiden)",
      "dist": "1.600",
      "statut": "DP-P/93"
    },
    "matauri queen f.ps. 3 a. | 05/02/2026 | pornichet | marais salants | 2.100": {
      "horse": "MATAURI QUEEN F.PS. 3 a.",
      "horseUrl": "https://www.france-galop.com/fr/cheval/dXhEZzBJdXdYKzl4RHdHUGZ2R0kzUT09",
      "date": "05/02/2026",
      "track": "PORNICHET",
      "race": "MARAIS SALANTS",
      "raceUrl": "https://www.france-galop.com/fr/course/detail/2026/P/M0F5TTVwSVRTWWJ5ZjNRRkROQmcyUT09",
      "cat": "HAND.",
      "dist": "2.100",
      "statut": "DP-P/3075"
    },
    "no tune (gb) f.ps. 3 a. | 06/02/2026 | deauville | priolo | 1.300": {
      "horse": "NO TUNE (GB) F.PS. 3 a.",
      "horseUrl": "https://www.france-galop.com/fr/cheval/QnhqdXA4MERPdXZveTZNNGVDeUNaZz09",
      "date": "06/02/2026",
      "track": "DEAUVILLE",
      "race": "PRIOLO",
      "raceUrl": "https://www.france-galop.com/fr/course/detail/2026/P/YWdkMGpKdDl2dCtYZklxNnFyUEprZz09",
      "cat": "(Classe 1)",
      "dist": "1.300",
      "statut": "DP-P/100"
    }
  },
  "newEngagements": {},
  "statusUpdates": {},
  "lastPosted": null
}